{
  "Villarreal|1998": [
    {
      "name": "Reina",
      "pos": "GK",
      "age": 30,
      "velocidad": 56,
      "resistencia": 76,
      "agresividad": 72,
      "calidad": 70
    },
    {
      "name": "Javi Venta",
      "pos": "DF",
      "age": 22,
      "velocidad": 74,
      "resistencia": 78,
      "agresividad": 76,
      "calidad": 68
    },
    {
      "name": "Arruabarrena",
      "pos": "DF",
      "age": 29,
      "velocidad": 68,
      "resistencia": 78,
      "agresividad": 80,
      "calidad": 70
    },
    {
      "name": "Quique Álvarez",
      "pos": "DF",
      "age": 26,
      "velocidad": 70,
      "resistencia": 80,
      "agresividad": 78,
      "calidad": 72
    },
    {
      "name": "Capdevila",
      "pos": "DF",
      "age": 22,
      "velocidad": 76,
      "resistencia": 80,
      "agresividad": 76,
      "calidad": 72
    },
    {
      "name": "Coloccini",
      "pos": "DF",
      "age": 17,
      "velocidad": 72,
      "resistencia": 74,
      "agresividad": 74,
      "calidad": 68
    },
    {
      "name": "Héctor Font",
      "pos": "MF",
      "age": 27,
      "velocidad": 70,
      "resistencia": 76,
      "agresividad": 74,
      "calidad": 68
    },
    {
      "name": "Cani",
      "pos": "MF",
      "age": 18,
      "velocidad": 76,
      "resistencia": 74,
      "agresividad": 70,
      "calidad": 68
    },
    {
      "name": "Sergio",
      "pos": "MF",
      "age": 24,
      "velocidad": 72,
      "resistencia": 76,
      "agresividad": 72,
      "calidad": 66
    },
    {
      "name": "Guillermo Amor",
      "pos": "MF",
      "age": 30,
      "velocidad": 68,
      "resistencia": 76,
      "agresividad": 72,
      "calidad": 74
    },
    {
      "name": "Penas",
      "pos": "MF",
      "age": 26,
      "velocidad": 70,
      "resistencia": 74,
      "agresividad": 72,
      "calidad": 66
    },
    {
      "name": "Darío Silva",
      "pos": "AT",
      "age": 27,
      "velocidad": 84,
      "resistencia": 76,
      "agresividad": 78,
      "calidad": 76
    },
    {
      "name": "Rodríguez",
      "pos": "AT",
      "age": 24,
      "velocidad": 78,
      "resistencia": 74,
      "agresividad": 72,
      "calidad": 68
    },
    {
      "name": "Llorente",
      "pos": "AT",
      "age": 23,
      "velocidad": 76,
      "resistencia": 74,
      "agresividad": 70,
      "calidad": 66
    }
  ],
  "Villarreal|2003": [
    {
      "name": "Diego López",
      "pos": "GK",
      "age": 22,
      "velocidad": 60,
      "resistencia": 78,
      "agresividad": 76,
      "calidad": 78
    },
    {
      "name": "Javi Venta",
      "pos": "DF",
      "age": 27,
      "velocidad": 75,
      "resistencia": 80,
      "agresividad": 78,
      "calidad": 74
    },
    {
      "name": "Quique Álvarez",
      "pos": "DF",
      "age": 31,
      "velocidad": 68,
      "resistencia": 78,
      "agresividad": 78,
      "calidad": 72
    },
    {
      "name": "Coloccini",
      "pos": "DF",
      "age": 22,
      "velocidad": 76,
      "resistencia": 78,
      "agresividad": 78,
      "calidad": 76
    },
    {
      "name": "Rodri",
      "pos": "DF",
      "age": 26,
      "velocidad": 72,
      "resistencia": 78,
      "agresividad": 76,
      "calidad": 70
    },
    {
      "name": "Marcos Senna",
      "pos": "MF",
      "age": 27,
      "velocidad": 72,
      "resistencia": 84,
      "agresividad": 82,
      "calidad": 80
    },
    {
      "name": "Riquelme",
      "pos": "MF",
      "age": 25,
      "velocidad": 72,
      "resistencia": 80,
      "agresividad": 78,
      "calidad": 90
    },
    {
      "name": "Cani",
      "pos": "MF",
      "age": 23,
      "velocidad": 80,
      "resistencia": 78,
      "agresividad": 74,
      "calidad": 76
    },
    {
      "name": "Josico",
      "pos": "MF",
      "age": 27,
      "velocidad": 74,
      "resistencia": 82,
      "agresividad": 80,
      "calidad": 74
    },
    {
      "name": "Valdo",
      "pos": "MF",
      "age": 28,
      "velocidad": 70,
      "resistencia": 76,
      "agresividad": 74,
      "calidad": 70
    },
    {
      "name": "Sonny Anderson",
      "pos": "AT",
      "age": 33,
      "velocidad": 78,
      "resistencia": 72,
      "agresividad": 76,
      "calidad": 78
    },
    {
      "name": "Guayre",
      "pos": "AT",
      "age": 25,
      "velocidad": 80,
      "resistencia": 74,
      "agresividad": 72,
      "calidad": 72
    },
    {
      "name": "José Mari",
      "pos": "AT",
      "age": 25,
      "velocidad": 78,
      "resistencia": 74,
      "agresividad": 74,
      "calidad": 72
    },
    {
      "name": "Arruabarrena",
      "pos": "DF",
      "age": 34,
      "velocidad": 62,
      "resistencia": 74,
      "agresividad": 78,
      "calidad": 66
    }
  ],
  "Villarreal|2004": [
    {
      "name": "Diego López",
      "pos": "GK",
      "age": 23,
      "velocidad": 62,
      "resistencia": 80,
      "agresividad": 76,
      "calidad": 80
    },
    {
      "name": "Javi Venta",
      "pos": "DF",
      "age": 28,
      "velocidad": 75,
      "resistencia": 80,
      "agresividad": 78,
      "calidad": 74
    },
    {
      "name": "Quique Álvarez",
      "pos": "DF",
      "age": 32,
      "velocidad": 66,
      "resistencia": 76,
      "agresividad": 78,
      "calidad": 72
    },
    {
      "name": "Coloccini",
      "pos": "DF",
      "age": 23,
      "velocidad": 76,
      "resistencia": 80,
      "agresividad": 80,
      "calidad": 78
    },
    {
      "name": "Capdevila",
      "pos": "DF",
      "age": 28,
      "velocidad": 76,
      "resistencia": 82,
      "agresividad": 78,
      "calidad": 78
    },
    {
      "name": "Marcos Senna",
      "pos": "MF",
      "age": 28,
      "velocidad": 72,
      "resistencia": 86,
      "agresividad": 84,
      "calidad": 82
    },
    {
      "name": "Riquelme",
      "pos": "MF",
      "age": 26,
      "velocidad": 72,
      "resistencia": 82,
      "agresividad": 80,
      "calidad": 93
    },
    {
      "name": "Cani",
      "pos": "MF",
      "age": 24,
      "velocidad": 80,
      "resistencia": 78,
      "agresividad": 74,
      "calidad": 78
    },
    {
      "name": "Josico",
      "pos": "MF",
      "age": 28,
      "velocidad": 74,
      "resistencia": 82,
      "agresividad": 80,
      "calidad": 75
    },
    {
      "name": "Forlán",
      "pos": "AT",
      "age": 25,
      "velocidad": 82,
      "resistencia": 82,
      "agresividad": 80,
      "calidad": 86
    },
    {
      "name": "José Mari",
      "pos": "AT",
      "age": 26,
      "velocidad": 78,
      "resistencia": 76,
      "agresividad": 76,
      "calidad": 74
    },
    {
      "name": "Guayre",
      "pos": "AT",
      "age": 26,
      "velocidad": 80,
      "resistencia": 74,
      "agresividad": 72,
      "calidad": 72
    },
    {
      "name": "Rodri",
      "pos": "DF",
      "age": 27,
      "velocidad": 72,
      "resistencia": 78,
      "agresividad": 76,
      "calidad": 70
    },
    {
      "name": "Valdo",
      "pos": "MF",
      "age": 29,
      "velocidad": 69,
      "resistencia": 75,
      "agresividad": 72,
      "calidad": 68
    }
  ],
  "Villarreal|2005": [
    {
      "name": "Diego López",
      "pos": "GK",
      "age": 24,
      "velocidad": 63,
      "resistencia": 82,
      "agresividad": 78,
      "calidad": 83
    },
    {
      "name": "Javi Venta",
      "pos": "DF",
      "age": 29,
      "velocidad": 74,
      "resistencia": 80,
      "agresividad": 78,
      "calidad": 76
    },
    {
      "name": "Quique Álvarez",
      "pos": "DF",
      "age": 33,
      "velocidad": 64,
      "resistencia": 74,
      "agresividad": 76,
      "calidad": 70
    },
    {
      "name": "Coloccini",
      "pos": "DF",
      "age": 24,
      "velocidad": 77,
      "resistencia": 82,
      "agresividad": 82,
      "calidad": 80
    },
    {
      "name": "Capdevila",
      "pos": "DF",
      "age": 29,
      "velocidad": 76,
      "resistencia": 84,
      "agresividad": 80,
      "calidad": 80
    },
    {
      "name": "Marcos Senna",
      "pos": "MF",
      "age": 29,
      "velocidad": 72,
      "resistencia": 88,
      "agresividad": 86,
      "calidad": 84
    },
    {
      "name": "Riquelme",
      "pos": "MF",
      "age": 27,
      "velocidad": 73,
      "resistencia": 84,
      "agresividad": 80,
      "calidad": 95
    },
    {
      "name": "Cani",
      "pos": "MF",
      "age": 25,
      "velocidad": 82,
      "resistencia": 80,
      "agresividad": 76,
      "calidad": 80
    },
    {
      "name": "Josico",
      "pos": "MF",
      "age": 29,
      "velocidad": 74,
      "resistencia": 84,
      "agresividad": 82,
      "calidad": 76
    },
    {
      "name": "Forlán",
      "pos": "AT",
      "age": 26,
      "velocidad": 83,
      "resistencia": 84,
      "agresividad": 82,
      "calidad": 88
    },
    {
      "name": "José Mari",
      "pos": "AT",
      "age": 27,
      "velocidad": 78,
      "resistencia": 76,
      "agresividad": 76,
      "calidad": 74
    },
    {
      "name": "Alessio Tacchinardi",
      "pos": "MF",
      "age": 31,
      "velocidad": 68,
      "resistencia": 80,
      "agresividad": 82,
      "calidad": 74
    },
    {
      "name": "Rodri",
      "pos": "DF",
      "age": 28,
      "velocidad": 72,
      "resistencia": 78,
      "agresividad": 76,
      "calidad": 70
    },
    {
      "name": "Guayre",
      "pos": "AT",
      "age": 27,
      "velocidad": 80,
      "resistencia": 74,
      "agresividad": 72,
      "calidad": 72
    }
  ],
  "Villarreal|2006": [
    {
      "name": "Diego López",
      "pos": "GK",
      "age": 25,
      "velocidad": 64,
      "resistencia": 82,
      "agresividad": 78,
      "calidad": 84
    },
    {
      "name": "Javi Venta",
      "pos": "DF",
      "age": 30,
      "velocidad": 73,
      "resistencia": 80,
      "agresividad": 78,
      "calidad": 76
    },
    {
      "name": "Capdevila",
      "pos": "DF",
      "age": 30,
      "velocidad": 76,
      "resistencia": 84,
      "agresividad": 80,
      "calidad": 80
    },
    {
      "name": "Coloccini",
      "pos": "DF",
      "age": 25,
      "velocidad": 77,
      "resistencia": 82,
      "agresividad": 82,
      "calidad": 80
    },
    {
      "name": "González",
      "pos": "DF",
      "age": 26,
      "velocidad": 72,
      "resistencia": 80,
      "agresividad": 78,
      "calidad": 72
    },
    {
      "name": "Marcos Senna",
      "pos": "MF",
      "age": 30,
      "velocidad": 71,
      "resistencia": 88,
      "agresividad": 86,
      "calidad": 85
    },
    {
      "name": "Riquelme",
      "pos": "MF",
      "age": 28,
      "velocidad": 72,
      "resistencia": 82,
      "agresividad": 78,
      "calidad": 94
    },
    {
      "name": "Santi Cazorla",
      "pos": "MF",
      "age": 22,
      "velocidad": 84,
      "resistencia": 80,
      "agresividad": 74,
      "calidad": 82
    },
    {
      "name": "Cani",
      "pos": "MF",
      "age": 26,
      "velocidad": 82,
      "resistencia": 80,
      "agresividad": 76,
      "calidad": 80
    },
    {
      "name": "Robert Pires",
      "pos": "MF",
      "age": 33,
      "velocidad": 76,
      "resistencia": 76,
      "agresividad": 72,
      "calidad": 82
    },
    {
      "name": "Forlán",
      "pos": "AT",
      "age": 27,
      "velocidad": 83,
      "resistencia": 84,
      "agresividad": 82,
      "calidad": 89
    },
    {
      "name": "José Mari",
      "pos": "AT",
      "age": 28,
      "velocidad": 76,
      "resistencia": 74,
      "agresividad": 74,
      "calidad": 72
    },
    {
      "name": "Nihat",
      "pos": "AT",
      "age": 27,
      "velocidad": 82,
      "resistencia": 78,
      "agresividad": 74,
      "calidad": 78
    },
    {
      "name": "Rodri",
      "pos": "DF",
      "age": 29,
      "velocidad": 70,
      "resistencia": 78,
      "agresividad": 76,
      "calidad": 70
    }
  ],
  "Villarreal|2007": [
    {
      "name": "Diego López",
      "pos": "GK",
      "age": 26,
      "velocidad": 64,
      "resistencia": 82,
      "agresividad": 78,
      "calidad": 84
    },
    {
      "name": "Javi Venta",
      "pos": "DF",
      "age": 31,
      "velocidad": 72,
      "resistencia": 78,
      "agresividad": 76,
      "calidad": 74
    },
    {
      "name": "Capdevila",
      "pos": "DF",
      "age": 31,
      "velocidad": 75,
      "resistencia": 84,
      "agresividad": 80,
      "calidad": 80
    },
    {
      "name": "González",
      "pos": "DF",
      "age": 27,
      "velocidad": 72,
      "resistencia": 80,
      "agresividad": 78,
      "calidad": 72
    },
    {
      "name": "Godín",
      "pos": "DF",
      "age": 22,
      "velocidad": 76,
      "resistencia": 82,
      "agresividad": 84,
      "calidad": 78
    },
    {
      "name": "Marcos Senna",
      "pos": "MF",
      "age": 31,
      "velocidad": 70,
      "resistencia": 86,
      "agresividad": 84,
      "calidad": 84
    },
    {
      "name": "Santi Cazorla",
      "pos": "MF",
      "age": 23,
      "velocidad": 86,
      "resistencia": 82,
      "agresividad": 74,
      "calidad": 85
    },
    {
      "name": "Cani",
      "pos": "MF",
      "age": 27,
      "velocidad": 80,
      "resistencia": 80,
      "agresividad": 76,
      "calidad": 80
    },
    {
      "name": "Bruno Soriano",
      "pos": "MF",
      "age": 23,
      "velocidad": 72,
      "resistencia": 82,
      "agresividad": 80,
      "calidad": 76
    },
    {
      "name": "Nihat",
      "pos": "AT",
      "age": 28,
      "velocidad": 82,
      "resistencia": 78,
      "agresividad": 74,
      "calidad": 80
    },
    {
      "name": "Rossi",
      "pos": "AT",
      "age": 22,
      "velocidad": 84,
      "resistencia": 76,
      "agresividad": 72,
      "calidad": 80
    },
    {
      "name": "Llorente",
      "pos": "AT",
      "age": 32,
      "velocidad": 68,
      "resistencia": 76,
      "agresividad": 78,
      "calidad": 74
    },
    {
      "name": "Borja Valero",
      "pos": "MF",
      "age": 22,
      "velocidad": 74,
      "resistencia": 78,
      "agresividad": 72,
      "calidad": 74
    },
    {
      "name": "Cygan",
      "pos": "DF",
      "age": 33,
      "velocidad": 66,
      "resistencia": 76,
      "agresividad": 78,
      "calidad": 68
    }
  ],
  "Villarreal|2008": [
    {
      "name": "Diego López",
      "pos": "GK",
      "age": 27,
      "velocidad": 65,
      "resistencia": 82,
      "agresividad": 78,
      "calidad": 85
    },
    {
      "name": "Capdevila",
      "pos": "DF",
      "age": 32,
      "velocidad": 74,
      "resistencia": 82,
      "agresividad": 80,
      "calidad": 80
    },
    {
      "name": "González",
      "pos": "DF",
      "age": 28,
      "velocidad": 72,
      "resistencia": 80,
      "agresividad": 78,
      "calidad": 72
    },
    {
      "name": "Godín",
      "pos": "DF",
      "age": 23,
      "velocidad": 78,
      "resistencia": 84,
      "agresividad": 86,
      "calidad": 82
    },
    {
      "name": "Javi Venta",
      "pos": "DF",
      "age": 32,
      "velocidad": 70,
      "resistencia": 76,
      "agresividad": 74,
      "calidad": 72
    },
    {
      "name": "Marcos Senna",
      "pos": "MF",
      "age": 32,
      "velocidad": 68,
      "resistencia": 84,
      "agresividad": 84,
      "calidad": 84
    },
    {
      "name": "Santi Cazorla",
      "pos": "MF",
      "age": 24,
      "velocidad": 88,
      "resistencia": 84,
      "agresividad": 76,
      "calidad": 87
    },
    {
      "name": "Cani",
      "pos": "MF",
      "age": 28,
      "velocidad": 80,
      "resistencia": 80,
      "agresividad": 76,
      "calidad": 80
    },
    {
      "name": "Bruno Soriano",
      "pos": "MF",
      "age": 24,
      "velocidad": 72,
      "resistencia": 84,
      "agresividad": 80,
      "calidad": 78
    },
    {
      "name": "Borja Valero",
      "pos": "MF",
      "age": 23,
      "velocidad": 75,
      "resistencia": 80,
      "agresividad": 72,
      "calidad": 76
    },
    {
      "name": "Rossi",
      "pos": "AT",
      "age": 23,
      "velocidad": 85,
      "resistencia": 78,
      "agresividad": 74,
      "calidad": 83
    },
    {
      "name": "Nihat",
      "pos": "AT",
      "age": 29,
      "velocidad": 80,
      "resistencia": 76,
      "agresividad": 74,
      "calidad": 78
    },
    {
      "name": "Fuentes",
      "pos": "DF",
      "age": 30,
      "velocidad": 70,
      "resistencia": 78,
      "agresividad": 76,
      "calidad": 70
    },
    {
      "name": "Llorente",
      "pos": "AT",
      "age": 33,
      "velocidad": 66,
      "resistencia": 74,
      "agresividad": 76,
      "calidad": 72
    }
  ]
}